<?xml version="1.0" encoding="utf-8" ?>
<dwsync>
<file name="Environment.php" server="C:/xampp/htdocs/EOS/" local="130622292101755318" remote="130622292100000000" Dst="0" />
<file name="Log.php" server="C:/xampp/htdocs/EOS/" local="130622292111605469" remote="130622292110000000" Dst="0" />
<file name="LogWriter.php" server="C:/xampp/htdocs/EOS/" local="130622292111680471" remote="130622292110000000" Dst="0" />
<file name="Middleware.php" server="C:/xampp/htdocs/EOS/" local="130622292111730471" remote="130622292110000000" Dst="0" />
<file name="Route.php" server="C:/xampp/htdocs/EOS/" local="130622292116780549" remote="130622292110000000" Dst="0" />
<file name="Router.php" server="C:/xampp/htdocs/EOS/" local="130622292116830550" remote="130622292110000000" Dst="0" />
<file name="Slim.php" server="C:/xampp/htdocs/EOS/" local="130622292116880550" remote="130622292110000000" Dst="0" />
<file name="View.php" server="C:/xampp/htdocs/EOS/" local="130622292116930551" remote="130622292110000000" Dst="0" />
</dwsync>